{
  "POIs": [
    {
      "fit": [
        0.9581367373466492,
        1.0,
        1.0406992435455322
      ],
      "name": "r"
    }
  ],
  "method": "default",
  "params": [
    {
      "fit": [
        -0.9146166443824768,
        0.0,
        0.9186146855354309
      ],
      "groups": [
        "mySyst"
      ],
      "impact_r": 0.001071631908416748,
      "name": "BTagSF_b",
      "prefit": [
        -1.0,
        0.0,
        1.0
      ],
      "r": [
        0.9989283680915833,
        1.0,
        1.0004804134368896
      ],
      "type": "Gaussian"
    },
    {
      "fit": [
        -0.9065856337547302,
        1.8330874809180386e-06,
        0.9111359715461731
      ],
      "groups": [
        "mySyst"
      ],
      "impact_r": 0.0020509958267211914,
      "name": "BTagSF_l",
      "prefit": [
        -1.0,
        0.0,
        1.0
      ],
      "r": [
        0.9983729720115662,
        1.0,
        1.0020509958267212
      ],
      "type": "Gaussian"
    },
    {
      "fit": [
        -0.9940868020057678,
        0.0,
        0.9943844676017761
      ],
      "groups": [],
      "impact_r": 0.0,
      "name": "EleEff",
      "prefit": [
        -1.0,
        0.0,
        1.0
      ],
      "r": [
        1.0,
        1.0,
        1.0
      ],
      "type": "Gaussian"
    },
    {
      "fit": [
        0.7507666945457458,
        1.0,
        1.260040521621704
      ],
      "groups": [],
      "impact_r": 0.019262850284576416,
      "name": "IsoOtherSF",
      "prefit": [
        0.7,
        1.0,
        1.3
      ],
      "r": [
        1.0168826580047607,
        1.0,
        0.9807371497154236
      ],
      "type": "Gaussian"
    },
    {
      "fit": [
        0.9508363604545593,
        1.0,
        1.0494663715362549
      ],
      "groups": [],
      "impact_r": 0.0011057853698730469,
      "name": "IsoTTbarSF",
      "prefit": [
        0.9500000000000001,
        1.0,
        1.05
      ],
      "r": [
        1.001105785369873,
        1.0,
        0.9990331530570984
      ],
      "type": "Gaussian"
    },
    {
      "fit": [
        0.8159438967704773,
        0.9999999403953552,
        1.1840072870254517
      ],
      "groups": [],
      "impact_r": 0.00753939151763916,
      "name": "IsoWGammaSF",
      "prefit": [
        0.8099999999999999,
        1.0,
        1.19
      ],
      "r": [
        1.0068215131759644,
        1.0,
        0.9924606084823608
      ],
      "type": "Gaussian"
    },
    {
      "fit": [
        0.7918391227722168,
        0.9999999403953552,
        1.2082922458648682
      ],
      "groups": [],
      "impact_r": 0.0019792914390563965,
      "name": "IsoZGammaSF",
      "prefit": [
        0.79,
        1.0,
        1.21
      ],
      "r": [
        1.0016871690750122,
        1.0,
        0.9980207085609436
      ],
      "type": "Gaussian"
    },
    {
      "fit": [
        0.7916452288627625,
        1.0,
        1.2091013193130493
      ],
      "groups": [],
      "impact_r": 7.426738739013672e-05,
      "name": "IsoZJetsSF",
      "prefit": [
        0.79,
        1.0,
        1.21
      ],
      "r": [
        1.0000725984573364,
        1.0,
        0.9999257326126099
      ],
      "type": "Gaussian"
    },
    {
      "fit": [
        0.950353741645813,
        1.0,
        1.0491739511489868
      ],
      "groups": [],
      "impact_r": 0.0006988048553466797,
      "name": "MisIdSF",
      "prefit": [
        0.9500000000000001,
        1.0,
        1.05
      ],
      "r": [
        1.0006988048553467,
        1.0,
        0.9993435144424438
      ],
      "type": "Gaussian"
    },
    {
      "fit": [
        -0.9423992037773132,
        0.0,
        0.9440910816192627
      ],
      "groups": [],
      "impact_r": 0.0003326535224914551,
      "name": "MuEff",
      "prefit": [
        -1.0,
        0.0,
        1.0
      ],
      "r": [
        1.000012755393982,
        1.0,
        0.9996673464775085
      ],
      "type": "Gaussian"
    },
    {
      "fit": [
        0.738682746887207,
        1.0000001192092896,
        1.2563444375991821
      ],
      "groups": [],
      "impact_r": 0.008298635482788086,
      "name": "NpOtherSF",
      "prefit": [
        0.7,
        1.0,
        1.3
      ],
      "r": [
        0.9917013645172119,
        1.0,
        1.0052399635314941
      ],
      "type": "Gaussian"
    },
    {
      "fit": [
        0.9641658067703247,
        1.0,
        1.0331919193267822
      ],
      "groups": [],
      "impact_r": 0.007685482501983643,
      "name": "NpTTbarSF",
      "prefit": [
        0.9500000000000001,
        1.0,
        1.05
      ],
      "r": [
        0.9923145174980164,
        1.0,
        1.0040662288665771
      ],
      "type": "Gaussian"
    },
    {
      "fit": [
        0.8112241625785828,
        1.0,
        1.1890336275100708
      ],
      "groups": [],
      "impact_r": 3.314018249511719e-05,
      "name": "NpWGammaSF",
      "prefit": [
        0.8099999999999999,
        1.0,
        1.19
      ],
      "r": [
        0.9999673962593079,
        1.0,
        1.0000331401824951
      ],
      "type": "Gaussian"
    },
    {
      "fit": [
        0.7913568019866943,
        1.0,
        1.2089357376098633
      ],
      "groups": [],
      "impact_r": 6.377696990966797e-06,
      "name": "NpZGammaSF",
      "prefit": [
        0.79,
        1.0,
        1.21
      ],
      "r": [
        1.0000063180923462,
        1.0,
        0.999993622303009
      ],
      "type": "Gaussian"
    },
    {
      "fit": [
        0.7918704152107239,
        1.0000001192092896,
        1.208603858947754
      ],
      "groups": [],
      "impact_r": 0.00027871131896972656,
      "name": "NpZJetsSF",
      "prefit": [
        0.79,
        1.0,
        1.21
      ],
      "r": [
        1.0002787113189697,
        1.0,
        0.9997963309288025
      ],
      "type": "Gaussian"
    },
    {
      "fit": [
        -0.7462373971939087,
        2.0729896732518682e-06,
        0.7636339664459229
      ],
      "groups": [
        "mySyst"
      ],
      "impact_r": 0.001229703426361084,
      "name": "PU",
      "prefit": [
        -1.0,
        0.0,
        1.0
      ],
      "r": [
        1.0000649690628052,
        1.0,
        0.9987702965736389
      ],
      "type": "Gaussian"
    },
    {
      "fit": [
        -0.48308032751083374,
        2.401977781119058e-07,
        0.4840327501296997
      ],
      "groups": [
        "otherSyst"
      ],
      "impact_r": 0.016260623931884766,
      "name": "PhoEff",
      "prefit": [
        -1.0,
        0.0,
        1.0
      ],
      "r": [
        1.0153683423995972,
        1.0,
        0.9837393760681152
      ],
      "type": "Gaussian"
    },
    {
      "fit": [
        0.950437068939209,
        1.0,
        1.0498605966567993
      ],
      "groups": [],
      "impact_r": 0.0,
      "name": "TTbarSF",
      "prefit": [
        0.9500000000000001,
        1.0,
        1.05
      ],
      "r": [
        1.0,
        1.0,
        1.0
      ],
      "type": "Gaussian"
    },
    {
      "fit": [
        0.8235183358192444,
        1.000000238418579,
        1.1779937744140625
      ],
      "groups": [],
      "impact_r": 0.0003897547721862793,
      "name": "WGammaSF",
      "prefit": [
        0.8099999999999999,
        1.0,
        1.19
      ],
      "r": [
        0.9996102452278137,
        1.0,
        1.0000858306884766
      ],
      "type": "Gaussian"
    },
    {
      "fit": [
        0.7940860390663147,
        1.0000001192092896,
        1.2058197259902954
      ],
      "groups": [],
      "impact_r": 0.0003858208656311035,
      "name": "ZGammaSF",
      "prefit": [
        0.79,
        1.0,
        1.21
      ],
      "r": [
        0.9996141791343689,
        1.0,
        1.0002309083938599
      ],
      "type": "Gaussian"
    },
    {
      "fit": [
        0.9475743174552917,
        1.0,
        1.054887056350708
      ],
      "groups": [],
      "impact_r": 0.031999170780181885,
      "name": "ZJetsSF",
      "prefit": [
        0.79,
        1.0,
        1.21
      ],
      "r": [
        1.0310912132263184,
        1.0,
        0.9680008292198181
      ],
      "type": "Gaussian"
    },
    {
      "fit": [
        -0.7367632985115051,
        -2.7716316708392696e-06,
        0.7322172522544861
      ],
      "groups": [],
      "impact_r": 0.009807050228118896,
      "name": "fsr",
      "prefit": [
        -1.0,
        0.0,
        1.0
      ],
      "r": [
        0.9901929497718811,
        1.0,
        0.9917754530906677
      ],
      "type": "Gaussian"
    },
    {
      "fit": [
        -0.7062987685203552,
        0.0,
        0.7538543343544006
      ],
      "groups": [],
      "impact_r": 0.011018455028533936,
      "name": "isr",
      "prefit": [
        -1.0,
        0.0,
        1.0
      ],
      "r": [
        0.9889815449714661,
        1.0,
        1.0066750049591064
      ],
      "type": "Gaussian"
    },
    {
      "fit": [
        -0.4698373079299927,
        3.4558519246274955e-07,
        0.4752596318721771
      ],
      "groups": [
        "mySyst"
      ],
      "impact_r": 0.0005764961242675781,
      "name": "lumi_13TeV",
      "prefit": [
        -0.9999999999999999,
        0.0,
        0.9999999999999999
      ],
      "r": [
        1.0005764961242676,
        1.0,
        0.9995516538619995
      ],
      "type": "Gaussian"
    },
    {
      "fit": [
        -0.2523227632045746,
        1.0572030362254736e-07,
        0.3670644164085388
      ],
      "groups": [],
      "impact_r": 0.015070915222167969,
      "name": "prop_binch1_bin0",
      "prefit": [
        -0.9999999999999999,
        0.0,
        0.9999999999999999
      ],
      "r": [
        0.9851374626159668,
        1.0,
        1.015070915222168
      ],
      "type": "Gaussian"
    },
    {
      "fit": [
        -0.7692579627037048,
        1.8476119123533863e-07,
        0.7843319773674011
      ],
      "groups": [],
      "impact_r": 0.004363536834716797,
      "name": "prop_binch1_bin1",
      "prefit": [
        -0.9999999999999999,
        0.0,
        0.9999999999999999
      ],
      "r": [
        1.0043635368347168,
        1.0,
        0.9983567595481873
      ],
      "type": "Gaussian"
    },
    {
      "fit": [
        -0.9395024180412292,
        -5.1338943762857525e-08,
        0.940414547920227
      ],
      "groups": [],
      "impact_r": 0.0042989253997802734,
      "name": "prop_binch1_bin2",
      "prefit": [
        -0.9999999999999999,
        0.0,
        0.9999999999999999
      ],
      "r": [
        1.0042989253997803,
        1.0,
        0.9960182309150696
      ],
      "type": "Gaussian"
    },
    {
      "fit": [
        -0.9514065384864807,
        -3.7969255117786815e-07,
        0.9508532881736755
      ],
      "groups": [],
      "impact_r": 0.0066307783126831055,
      "name": "prop_binch1_bin3",
      "prefit": [
        -0.9999999999999999,
        0.0,
        0.9999999999999999
      ],
      "r": [
        1.006630778312683,
        1.0,
        0.9935208559036255
      ],
      "type": "Gaussian"
    },
    {
      "fit": [
        -0.9460740089416504,
        -1.8188111994277278e-07,
        0.9447068572044373
      ],
      "groups": [],
      "impact_r": 0.004849493503570557,
      "name": "prop_binch1_bin4",
      "prefit": [
        -0.9999999999999999,
        0.0,
        0.9999999999999999
      ],
      "r": [
        1.0046249628067017,
        1.0,
        0.9951505064964294
      ],
      "type": "Gaussian"
    },
    {
      "fit": [
        -0.9190331697463989,
        -3.898371687682811e-07,
        0.9198195934295654
      ],
      "groups": [],
      "impact_r": 0.001741170883178711,
      "name": "prop_binch1_bin5",
      "prefit": [
        -0.9999999999999999,
        0.0,
        0.9999999999999999
      ],
      "r": [
        1.0017411708831787,
        1.0,
        0.9985589385032654
      ],
      "type": "Gaussian"
    },
    {
      "fit": [
        -0.8948246836662292,
        1.96868526813887e-07,
        0.8998636603355408
      ],
      "groups": [],
      "impact_r": 0.0010541677474975586,
      "name": "prop_binch1_bin6",
      "prefit": [
        -0.9999999999999999,
        0.0,
        0.9999999999999999
      ],
      "r": [
        1.0010541677474976,
        1.0,
        0.99944007396698
      ],
      "type": "Gaussian"
    },
    {
      "fit": [
        -0.9197573065757751,
        -1.9118179750421405e-07,
        0.9209097623825073
      ],
      "groups": [],
      "impact_r": 0.0026053786277770996,
      "name": "prop_binch1_bin7",
      "prefit": [
        -0.9999999999999999,
        0.0,
        0.9999999999999999
      ],
      "r": [
        0.9973946213722229,
        1.0,
        1.0016909837722778
      ],
      "type": "Gaussian"
    },
    {
      "fit": [
        -0.5036653876304626,
        0.0,
        0.5066618323326111
      ],
      "groups": [],
      "impact_r": 0.0011879801750183105,
      "name": "prop_binch2_bin0",
      "prefit": [
        -0.9999999999999999,
        0.0,
        0.9999999999999999
      ],
      "r": [
        0.9988120198249817,
        1.0,
        1.000914454460144
      ],
      "type": "Gaussian"
    },
    {
      "fit": [
        -0.3100878894329071,
        2.530936399125494e-06,
        0.29532110691070557
      ],
      "groups": [],
      "impact_r": 0.0007433295249938965,
      "name": "prop_binch2_bin1",
      "prefit": [
        -0.9999999999999999,
        0.0,
        0.9999999999999999
      ],
      "r": [
        0.9992566704750061,
        1.0,
        1.0004796981811523
      ],
      "type": "Gaussian"
    },
    {
      "fit": [
        -0.3942736089229584,
        1.5148061720537953e-06,
        0.3935734033584595
      ],
      "groups": [],
      "impact_r": 0.00033032894134521484,
      "name": "prop_binch2_bin2",
      "prefit": [
        -0.9999999999999999,
        0.0,
        0.9999999999999999
      ],
      "r": [
        1.0003293752670288,
        1.0,
        1.0003303289413452
      ],
      "type": "Gaussian"
    },
    {
      "fit": [
        -0.426482230424881,
        0.0,
        0.4294983446598053
      ],
      "groups": [],
      "impact_r": 0.0007756948471069336,
      "name": "prop_binch2_bin3",
      "prefit": [
        -0.9999999999999999,
        0.0,
        0.9999999999999999
      ],
      "r": [
        1.0007046461105347,
        1.0,
        0.9992243051528931
      ],
      "type": "Gaussian"
    },
    {
      "fit": [
        -0.6834354400634766,
        3.4069400953740114e-06,
        0.6831731796264648
      ],
      "groups": [],
      "impact_r": 0.0002944469451904297,
      "name": "prop_binch2_bin4",
      "prefit": [
        -0.9999999999999999,
        0.0,
        0.9999999999999999
      ],
      "r": [
        0.9998061656951904,
        1.0,
        0.9997055530548096
      ],
      "type": "Gaussian"
    },
    {
      "fit": [
        -0.4179075062274933,
        0.0,
        0.42542603611946106
      ],
      "groups": [],
      "impact_r": 0.00035387277603149414,
      "name": "prop_binch2_bin5",
      "prefit": [
        -0.9999999999999999,
        0.0,
        0.9999999999999999
      ],
      "r": [
        0.9996461272239685,
        1.0,
        1.0000799894332886
      ],
      "type": "Gaussian"
    },
    {
      "fit": [
        -0.34915292263031006,
        -1.043650513565808e-06,
        0.3520282804965973
      ],
      "groups": [],
      "impact_r": 0.0014759302139282227,
      "name": "prop_binch2_bin6",
      "prefit": [
        -0.9999999999999999,
        0.0,
        0.9999999999999999
      ],
      "r": [
        0.9985240697860718,
        1.0,
        1.0014199018478394
      ],
      "type": "Gaussian"
    },
    {
      "fit": [
        -0.6523394584655762,
        1.459641339351947e-06,
        0.6550254225730896
      ],
      "groups": [],
      "impact_r": 0.002988457679748535,
      "name": "prop_binch2_bin7",
      "prefit": [
        -0.9999999999999999,
        0.0,
        0.9999999999999999
      ],
      "r": [
        0.9973164796829224,
        1.0,
        1.0029884576797485
      ],
      "type": "Gaussian"
    },
    {
      "fit": [
        -0.9137101769447327,
        -6.418121643037011e-07,
        0.9166224002838135
      ],
      "groups": [],
      "impact_r": 0.00276029109954834,
      "name": "prop_binch3_bin0",
      "prefit": [
        -0.9999999999999999,
        0.0,
        0.9999999999999999
      ],
      "r": [
        1.0027602910995483,
        1.0,
        0.9976505637168884
      ],
      "type": "Gaussian"
    },
    {
      "fit": [
        -0.9152004718780518,
        3.8179135231075634e-07,
        0.917716920375824
      ],
      "groups": [],
      "impact_r": 0.001519322395324707,
      "name": "prop_binch3_bin1",
      "prefit": [
        -0.9999999999999999,
        0.0,
        0.9999999999999999
      ],
      "r": [
        1.0015193223953247,
        1.0,
        0.9987404346466064
      ],
      "type": "Gaussian"
    },
    {
      "fit": [
        -0.9312307834625244,
        4.1883072299242485e-07,
        0.9326299428939819
      ],
      "groups": [],
      "impact_r": 0.0001531839370727539,
      "name": "prop_binch3_bin2",
      "prefit": [
        -0.9999999999999999,
        0.0,
        0.9999999999999999
      ],
      "r": [
        1.0001531839370728,
        1.0,
        0.9999053478240967
      ],
      "type": "Gaussian"
    },
    {
      "fit": [
        -0.9439123272895813,
        4.3512832803571655e-07,
        0.9465795159339905
      ],
      "groups": [],
      "impact_r": 0.002093791961669922,
      "name": "prop_binch3_bin3",
      "prefit": [
        -0.9999999999999999,
        0.0,
        0.9999999999999999
      ],
      "r": [
        0.9979062080383301,
        1.0,
        1.0014660358428955
      ],
      "type": "Gaussian"
    },
    {
      "fit": [
        -0.6223342418670654,
        5.581333084592188e-07,
        0.6674609780311584
      ],
      "groups": [],
      "impact_r": 0.009976506233215332,
      "name": "prop_binch3_bin4",
      "prefit": [
        -0.9999999999999999,
        0.0,
        0.9999999999999999
      ],
      "r": [
        0.9940229058265686,
        1.0,
        1.0099765062332153
      ],
      "type": "Gaussian"
    },
    {
      "fit": [
        -0.9293464422225952,
        7.837472821847769e-07,
        0.9312403202056885
      ],
      "groups": [],
      "impact_r": 0.006353139877319336,
      "name": "prop_binch4_bin0",
      "prefit": [
        -0.9999999999999999,
        0.0,
        0.9999999999999999
      ],
      "r": [
        0.9936468601226807,
        1.0,
        1.0062410831451416
      ],
      "type": "Gaussian"
    },
    {
      "fit": [
        -0.9053957462310791,
        -2.545177153479017e-07,
        0.9097113013267517
      ],
      "groups": [],
      "impact_r": 0.00409311056137085,
      "name": "prop_binch4_bin1",
      "prefit": [
        -0.9999999999999999,
        0.0,
        0.9999999999999999
      ],
      "r": [
        0.9959068894386292,
        1.0,
        1.0040212869644165
      ],
      "type": "Gaussian"
    },
    {
      "fit": [
        -0.8252043724060059,
        5.7133142661314196e-09,
        0.8352006077766418
      ],
      "groups": [],
      "impact_r": 0.0002390146255493164,
      "name": "prop_binch5_bin0",
      "prefit": [
        -0.9999999999999999,
        0.0,
        0.9999999999999999
      ],
      "r": [
        1.0001912117004395,
        1.0,
        0.9997609853744507
      ],
      "type": "Gaussian"
    },
    {
      "fit": [
        -0.7838338017463684,
        2.2480659822576854e-07,
        0.7913885116577148
      ],
      "groups": [],
      "impact_r": 0.0005282759666442871,
      "name": "prop_binch5_bin1",
      "prefit": [
        -0.9999999999999999,
        0.0,
        0.9999999999999999
      ],
      "r": [
        1.0005038976669312,
        1.0,
        0.9994717240333557
      ],
      "type": "Gaussian"
    },
    {
      "fit": [
        -0.7382346987724304,
        3.9159408515843097e-07,
        0.747296929359436
      ],
      "groups": [],
      "impact_r": 0.0008949637413024902,
      "name": "prop_binch5_bin2",
      "prefit": [
        -0.9999999999999999,
        0.0,
        0.9999999999999999
      ],
      "r": [
        1.0008773803710938,
        1.0,
        0.9991050362586975
      ],
      "type": "Gaussian"
    },
    {
      "fit": [
        -0.7178447246551514,
        6.091481736802962e-07,
        0.7265958189964294
      ],
      "groups": [],
      "impact_r": 0.0008418560028076172,
      "name": "prop_binch5_bin3",
      "prefit": [
        -0.9999999999999999,
        0.0,
        0.9999999999999999
      ],
      "r": [
        1.000819444656372,
        1.0,
        0.9991581439971924
      ],
      "type": "Gaussian"
    },
    {
      "fit": [
        -0.7375999093055725,
        -4.260133152911294e-07,
        0.7445570230484009
      ],
      "groups": [],
      "impact_r": 0.001428842544555664,
      "name": "prop_binch5_bin4",
      "prefit": [
        -0.9999999999999999,
        0.0,
        0.9999999999999999
      ],
      "r": [
        1.0014288425445557,
        1.0,
        0.9987627863883972
      ],
      "type": "Gaussian"
    },
    {
      "fit": [
        -0.7897506356239319,
        6.094634130704435e-09,
        0.7953046560287476
      ],
      "groups": [],
      "impact_r": 0.001270294189453125,
      "name": "prop_binch5_bin5",
      "prefit": [
        -0.9999999999999999,
        0.0,
        0.9999999999999999
      ],
      "r": [
        1.0012702941894531,
        1.0,
        0.9990569949150085
      ],
      "type": "Gaussian"
    },
    {
      "fit": [
        -0.743137538433075,
        3.829435435420692e-09,
        0.7507542371749878
      ],
      "groups": [],
      "impact_r": 0.0009347200393676758,
      "name": "prop_binch5_bin6",
      "prefit": [
        -0.9999999999999999,
        0.0,
        0.9999999999999999
      ],
      "r": [
        1.000925898551941,
        1.0,
        0.9990652799606323
      ],
      "type": "Gaussian"
    },
    {
      "fit": [
        -0.7299970984458923,
        5.7210360893122925e-09,
        0.7378504276275635
      ],
      "groups": [],
      "impact_r": 0.0006695985794067383,
      "name": "prop_binch5_bin7",
      "prefit": [
        -0.9999999999999999,
        0.0,
        0.9999999999999999
      ],
      "r": [
        1.0006695985794067,
        1.0,
        0.999447762966156
      ],
      "type": "Gaussian"
    },
    {
      "fit": [
        -0.7555387616157532,
        7.422286785185861e-09,
        0.763515055179596
      ],
      "groups": [],
      "impact_r": 0.00044345855712890625,
      "name": "prop_binch5_bin8",
      "prefit": [
        -0.9999999999999999,
        0.0,
        0.9999999999999999
      ],
      "r": [
        1.000443458557129,
        1.0,
        0.9996261596679688
      ],
      "type": "Gaussian"
    },
    {
      "fit": [
        -0.7777267098426819,
        -2.2027084867204394e-07,
        0.7859272956848145
      ],
      "groups": [],
      "impact_r": 0.0006102323532104492,
      "name": "prop_binch5_bin9",
      "prefit": [
        -0.9999999999999999,
        0.0,
        0.9999999999999999
      ],
      "r": [
        1.0005797147750854,
        1.0,
        0.9993897676467896
      ],
      "type": "Gaussian"
    }
  ]
}
